README.md
openassist/__init__.py
openassist/openassist.py
openassist-2.2.7.dist-info/LICENSE
openassist-2.2.7.dist-info/METADATA
openassist-2.2.7.dist-info/WHEEL
openassist-2.2.7.dist-info/RECORD
