Metadata-Version: 2.1
Name: openassist
Version: 2.2.7
Summary: OpenAssist is a module for Python that allows you to create an AI assistant using import openai with ease.
License: MIT
Author: Free Zoloft
Author-email: mybusinessemaildbb@gmail.com
Requires-Python: >=3.10,<4.0
Classifier: License :: OSI Approved :: MIT License
Classifier: Programming Language :: Python :: 3
Classifier: Programming Language :: Python :: 3.10
Classifier: Programming Language :: Python :: 3.11
Requires-Dist: openai (>=0.27.6,<0.28.0)
